setup.py
pyuntl/__init__.py
pyuntl/dc_structure.py
pyuntl/etd_ms_structure.py
pyuntl/form_logic.py
pyuntl/highwire_structure.py
pyuntl/metadata_generator.py
pyuntl/quality.py
pyuntl/untl_structure.py
pyuntl/untldoc.py
pyuntl/util.py
pyuntl.egg-info/PKG-INFO
pyuntl.egg-info/SOURCES.txt
pyuntl.egg-info/dependency_links.txt
pyuntl.egg-info/pbr.json
pyuntl.egg-info/requires.txt
pyuntl.egg-info/top_level.txt