Metadata-Version: 1.1
Name: pyuntl
Version: 1.0.1
Summary: read, write and modify UNTL metadata records
Home-page: https://github.com/unt-libraries/pyuntl
Author: Mark Phillips
Author-email: mark.phillips@unt.edu
License: BSD
Keywords: untl,metadata,digital libraries,records
Platform: UNKNOWN
Classifier: Natural Language :: English
Classifier: Programming Language :: Python
Classifier: Programming Language :: Python :: 2.7
